netbase/__init__.py
netbase/alle.py
netbase/extensions.py
netbase/netbase.py
netbase/netbase_native.py
Netbase-0.1.239.dist-info/METADATA
Netbase-0.1.239.dist-info/WHEEL
Netbase-0.1.239.dist-info/top_level.txt
Netbase-0.1.239.dist-info/RECORD
