Metadata-Version: 2.1
Name: Netbase
Version: 0.1.239
Summary: Netbase : Wikidata World Graph
Author: Pannous
Author-email: info@pannous.com
License: Apache2 license
Requires-Dist: dill
